rok4/__init__.py
rok4/enums.py
rok4/exceptions.py
rok4/layer.py
rok4/pyramid.py
rok4/raster.py
rok4/storage.py
rok4/style.py
rok4/tile_matrix_set.py
rok4/utils.py
rok4/vector.py
rok4-2.2.3.dist-info/LICENSE.txt
rok4-2.2.3.dist-info/METADATA
rok4-2.2.3.dist-info/WHEEL
rok4-2.2.3.dist-info/top_level.txt
rok4-2.2.3.dist-info/RECORD
