Metadata-Version: 2.1
Name: rok4
Version: 2.2.3
Summary: Python core libraries for ROK4 project
Author-email: Géoportail IGN Developers <tout_rdev@ign.fr>
License: 
Project-URL: Homepage, https://rok4.github.io/core-python
Project-URL: Bug Reports, https://github.com/rok4/core-python/issues
Project-URL: Changelog, https://rok4.github.io/core-python/latest/CHANGELOG/
Project-URL: Source, https://github.com/rok4/core-python
Keywords: ROK4,library,pyramid,tile matrix set,storage
Classifier: Development Status :: 3 - Alpha
Classifier: Topic :: Software Development :: Libraries
Classifier: License :: CeCILL-C Free Software License Agreement (CECILL-C)
Classifier: Programming Language :: Python :: 3
Classifier: Programming Language :: Python :: 3.8
Classifier: Programming Language :: Python :: 3.9
Classifier: Programming Language :: Python :: 3.10
Classifier: Programming Language :: Python :: 3.11
Classifier: Programming Language :: Python :: 3 :: Only
Requires-Python: >=3.8
License-File: LICENSE.txt
Requires-Dist: boto3>=1.26.54
Requires-Dist: mapbox-vector-tile>=2.0.1
Requires-Dist: numpy>=1.24.2
Requires-Dist: pillow>=10.0.1
Requires-Dist: requests>=2.30.0
Provides-Extra: dev
Requires-Dist: black; extra == "dev"
Requires-Dist: isort>=5.12.0; extra == "dev"
Requires-Dist: pre-commit<4,>3; extra == "dev"
Requires-Dist: ruff>=0.0.281; extra == "dev"
Provides-Extra: doc
Requires-Dist: pdoc3>=0.10.0; extra == "doc"
Provides-Extra: test
Requires-Dist: pytest>=7.1.2; extra == "test"
Requires-Dist: coverage>=7.0.5; extra == "test"
